tests/__init__.py
tests/test_client.py
zarinpal/__init__.py
zarinpal/client.py
zarinpal/exceptions.py
zarinpal/utils.py
zarinpal_python_sdk-0.2.dist-info/LICENSE
zarinpal_python_sdk-0.2.dist-info/METADATA
zarinpal_python_sdk-0.2.dist-info/WHEEL
zarinpal_python_sdk-0.2.dist-info/top_level.txt
zarinpal_python_sdk-0.2.dist-info/RECORD
