Metadata-Version: 2.1
Name: zarinpal-python-sdk
Version: 0.2
Summary: Zarinpal Payment Gateway SDK for Python
Home-page: https://github.com/MohamadHusein/zarinpal-python-sdk
Author: Mohammad Hossein
Author-email: mohamd.qorbani383@gmail.com
License: MIT
Keywords: zarinpal,payment,sdk,python
Classifier: Programming Language :: Python :: 3
Classifier: License :: OSI Approved :: MIT License
Classifier: Operating System :: OS Independent
Requires-Python: >=3.6
License-File: LICENSE
Requires-Dist: requests>=2.25.1
